src/__init__.py
src/iceberg.py
src/tools/__init__.py
src/tools/namespace.py
src/tools/query.py
src/tools/table.py
src/tools/test_namespace.py
src/tools/test_query.py
src/tools/test_table.py
iceberg_mcp_server-0.1.22.dist-info/WHEEL
iceberg_mcp_server-0.1.22.dist-info/entry_points.txt
iceberg_mcp_server-0.1.22.dist-info/METADATA
iceberg_mcp_server-0.1.22.dist-info/RECORD
