Metadata-Version: 2.4
Name: iceberg-mcp-server
Version: 0.1.22
Summary: MCP Server for Apache Iceberg
License-Expression: Apache-2.0
Classifier: Programming Language :: Python :: 3
Classifier: License :: OSI Approved :: Apache Software License
Requires-Dist: duckdb
Requires-Dist: fastexcel
Requires-Dist: fastmcp
Requires-Dist: polars
Requires-Dist: pyarrow
Requires-Dist: pydantic
Requires-Dist: pyiceberg[bigquery,duckdb,dynamodb,glue,hive,polars,pyarrow,pyiceberg-core,sql-postgres,sql-sqlite]
Requires-Dist: sentry-sdk
Requires-Python: >=3.12
Project-URL: homepage, https://pypi.org/project/iceberg-mcp-server/
Project-URL: source, https://github.com/dragonejt/iceberg-mcp-server.git
Project-URL: issues, https://github.com/dragonejt/iceberg-mcp-server/issues
Project-URL: documentation, https://github.com/dragonejt/iceberg-mcp-server/wiki
